LICENSE
MANIFEST.in
README.md
setup.cfg
setup.py
neom/.pylintrc
neom/__init__.py
neom/apps.py
neom/__pycache__/__init__.cpython-310.pyc
neom/__pycache__/__init__.cpython-39.pyc
neom/__pycache__/apps.cpython-310.pyc
neom/__pycache__/apps.cpython-39.pyc
neom/core/ioc.py
neom/core/__pycache__/ioc.cpython-310.pyc
neom/core/__pycache__/ioc.cpython-39.pyc
neom/ddd/shared.py
neom/ddd/staff.py
neom/ddd/__pycache__/shared.cpython-310.pyc
neom/ddd/__pycache__/staff.cpython-310.pyc
neom/kit/__init__.py
neom/kit/__pycache__/__init__.cpython-310.pyc
neom/kit/__pycache__/__init__.cpython-39.pyc
neom/kit/md2/__init__.py
neom/kit/md2/__pycache__/__init__.cpython-310.pyc
neom/kit/md2/__pycache__/__init__.cpython-39.pyc
neom/kit/md2/forms/__init__.py
neom/kit/md2/forms/fields.py
neom/kit/md2/forms/models.py
neom/kit/md2/forms/widgets.py
neom/kit/md2/forms/__pycache__/__init__.cpython-310.pyc
neom/kit/md2/forms/__pycache__/__init__.cpython-39.pyc
neom/kit/md2/forms/__pycache__/fields.cpython-310.pyc
neom/kit/md2/forms/__pycache__/fields.cpython-39.pyc
neom/kit/md2/forms/__pycache__/models.cpython-310.pyc
neom/kit/md2/forms/__pycache__/models.cpython-39.pyc
neom/kit/md2/forms/__pycache__/widgets.cpython-310.pyc
neom/kit/md2/forms/__pycache__/widgets.cpython-39.pyc
neom/kit/md2/templatetags/neom_md2.py
neom/kit/md2/templatetags/__pycache__/neom_md2.cpython-310.pyc
neom/kit/md2/templatetags/__pycache__/neom_md2.cpython-39.pyc
neom/kit/md2/views/__init__.py
neom/kit/md2/views/__pycache__/__init__.cpython-310.pyc
neom/kit/md2/views/__pycache__/__init__.cpython-39.pyc
neom/kit/md2/views/generic/__init__.py
neom/kit/md2/views/generic/edit.py
neom/kit/md2/views/generic/__pycache__/__init__.cpython-310.pyc
neom/kit/md2/views/generic/__pycache__/__init__.cpython-39.pyc
neom/kit/md2/views/generic/__pycache__/edit.cpython-310.pyc
neom/kit/md2/views/generic/__pycache__/edit.cpython-39.pyc
neom/kit/template/__init__.py
neom/kit/template/library.py
neompy_et.egg-info/PKG-INFO
neompy_et.egg-info/SOURCES.txt
neompy_et.egg-info/dependency_links.txt
neompy_et.egg-info/requires.txt
neompy_et.egg-info/top_level.txt
