Metadata-Version: 2.1
Name: neompy-et
Version: 0.0.17
Summary: Development tools for neomadas projects.
Home-page: https://github.com/neomadas/neompy/
Author: Sinek Dev Team
Author-email: sinek-dev@unknown.pe
License: BSD 3-Clause License
Classifier: Environment :: Web Environment
Classifier: Framework :: Django
Classifier: Framework :: Django :: 3.2
Classifier: Intended Audience :: Developers
Classifier: License :: OSI Approved :: BSD License
Classifier: Operating System :: OS Independent
Classifier: Programming Language :: Python
Classifier: Programming Language :: Python :: 3
Classifier: Programming Language :: Python :: 3 :: Only
Classifier: Programming Language :: Python :: 3.8
Classifier: Topic :: Internet :: WWW/HTTP
Classifier: Topic :: Internet :: WWW/HTTP :: Dynamic Content
Requires-Python: >=3.9
License-File: LICENSE
